{
  "project_info": {
    "project_number": "789318566167",
    "project_id": "ultimate-game-bea23",
    "storage_bucket": "ultimate-game-bea23.firebasestorage.app"
  },
  "client": [
    {
      "client_info": {
        "mobilesdk_app_id": "1:789318566167:android:2ef1c7ca46ddb15b89f752",
        "android_client_info": {
          "package_name": "com.company.hybridgame"
        }
      },
      "oauth_client": [],
      "api_key": [
        {
          "current_key": "AIzaSyBHYxEPajT4FMJzDoPhMfs7gXFpAaoT_JY"
        }
      ],
      "services": {
        "appinvite_service": {
          "other_platform_oauth_client": []
        }
      }
    }
  ],
  "configuration_version": "1"
}
